{
  "slug": "kruskals-minimum-spanning-tree",
  "name": "Kruskals Minimum Spanning Tree",
  "categories": ["greedyalgorithms"],
  "body": {},
  "implementations": {
    "c-plus-plus": {
      "dir": "greedy_algorithms/kruskals_minimum_spanning_tree.cpp",
      "url": "https://github.com/TheAlgorithms/c-plus-plus/tree/master/greedy_algorithms/kruskals_minimum_spanning_tree.cpp",
      "code": "<span class=\"hljs-meta\">#<span class=\"hljs-keyword\">include</span> <span class=\"hljs-string\">&lt;array&gt;</span></span>\n<span class=\"hljs-meta\">#<span class=\"hljs-keyword\">include</span> <span class=\"hljs-string\">&lt;iostream&gt;</span></span>\n\n<span class=\"hljs-function\"><span class=\"hljs-type\">void</span> <span class=\"hljs-title\">findMinimumEdge</span><span class=\"hljs-params\">(<span class=\"hljs-type\">int</span> INFINITY, std::array&lt;std::array&lt;<span class=\"hljs-type\">int</span>, <span class=\"hljs-number\">6</span>&gt;, <span class=\"hljs-number\">6</span>&gt; graph)</span> </span>{\n    <span class=\"hljs-keyword\">for</span> (<span class=\"hljs-type\">int</span> i = <span class=\"hljs-number\">0</span>; i &lt; graph.<span class=\"hljs-built_in\">size</span>(); i++) {\n        <span class=\"hljs-type\">int</span> min = INFINITY;\n        <span class=\"hljs-type\">int</span> minIndex = <span class=\"hljs-number\">0</span>;\n        <span class=\"hljs-keyword\">for</span> (<span class=\"hljs-type\">int</span> j = <span class=\"hljs-number\">0</span>; j &lt; graph.<span class=\"hljs-built_in\">size</span>(); j++) {\n            <span class=\"hljs-keyword\">if</span> (graph[i][j] != <span class=\"hljs-number\">0</span> &amp;&amp; graph[i][j] &lt; min) {\n                min = graph[i][j];\n                minIndex = j;\n            }\n        }\n        std::cout &lt;&lt; i &lt;&lt; <span class=\"hljs-string\">&quot;  -  &quot;</span> &lt;&lt; minIndex &lt;&lt; <span class=\"hljs-string\">&quot;\\t&quot;</span> &lt;&lt; graph[i][minIndex]\n                  &lt;&lt; std::endl;\n    }\n}\n\n<span class=\"hljs-function\"><span class=\"hljs-type\">int</span> <span class=\"hljs-title\">main</span><span class=\"hljs-params\">()</span> </span>{\n    <span class=\"hljs-keyword\">constexpr</span> <span class=\"hljs-type\">int</span> INFINITY = <span class=\"hljs-number\">99999</span>;\n    std::array&lt;std::array&lt;<span class=\"hljs-type\">int</span>, 6&gt;, 6&gt; graph{\n        <span class=\"hljs-number\">0</span>,        <span class=\"hljs-number\">4</span>,        <span class=\"hljs-number\">1</span>,        <span class=\"hljs-number\">4</span>,        INFINITY, INFINITY,\n        <span class=\"hljs-number\">4</span>,        <span class=\"hljs-number\">0</span>,        <span class=\"hljs-number\">3</span>,        <span class=\"hljs-number\">8</span>,        <span class=\"hljs-number\">3</span>,        INFINITY,\n        <span class=\"hljs-number\">1</span>,        <span class=\"hljs-number\">3</span>,        <span class=\"hljs-number\">0</span>,        INFINITY, <span class=\"hljs-number\">1</span>,        INFINITY,\n        <span class=\"hljs-number\">4</span>,        <span class=\"hljs-number\">8</span>,        INFINITY, <span class=\"hljs-number\">0</span>,        <span class=\"hljs-number\">5</span>,        <span class=\"hljs-number\">7</span>,\n        INFINITY, <span class=\"hljs-number\">3</span>,        <span class=\"hljs-number\">1</span>,        <span class=\"hljs-number\">5</span>,        <span class=\"hljs-number\">0</span>,        INFINITY,\n        INFINITY, INFINITY, INFINITY, <span class=\"hljs-number\">7</span>,        INFINITY, <span class=\"hljs-number\">0</span>};\n\n    <span class=\"hljs-built_in\">findMinimumEdge</span>(INFINITY, graph);\n    <span class=\"hljs-keyword\">return</span> <span class=\"hljs-number\">0</span>;\n}\n"
    }
  },
  "contributors": [
    {
      "name": "Anup Kumar Panwar",
      "email": "1anuppanwar@gmail.com",
      "commits": 1
    },
    {
      "name": "Libin Yang",
      "email": "szuyanglb@outlook.com",
      "commits": 1
    },
    {
      "name": "Krishna Vedala",
      "email": "7001608+kvedala@users.noreply.github.com",
      "commits": 1
    },
    {
      "name": "Kaustubh Damania",
      "email": "kaustubh.damania@gmail.com",
      "commits": 1
    },
    {
      "name": "x0rld",
      "email": "45242856+x0rld@users.noreply.github.com",
      "commits": 1
    }
  ],
  "explanationUrl": {}
}
