{
  "slug": "minone",
  "name": "Minone",
  "categories": ["geneticalgorithm", "minimizationofpolynomialfunction"],
  "body": {},
  "implementations": {
    "matlab-octave": {
      "dir": "algorithms/Genetic-Algorithm/Minimization of polynomial function/minone.m",
      "url": "https://github.com/TheAlgorithms/matlab-octave/tree/master/algorithms/Genetic-Algorithm/Minimization of polynomial function/minone.m",
      "code": "<span class=\"hljs-function\"><span class=\"hljs-keyword\">function</span> <span class=\"hljs-title\">z</span>= <span class=\"hljs-title\">minone</span><span class=\"hljs-params\">(x)</span></span>\n    z = sum(x.^<span class=\"hljs-number\">2</span>);\n<span class=\"hljs-keyword\">end</span>"
    }
  },
  "contributors": [
    {
      "name": "Abhishek Maletha",
      "email": "67141747+Abhishek-photon@users.noreply.github.com",
      "commits": 1
    }
  ],
  "explanationUrl": {}
}
