{
  "slug": "monte-carlo-dice",
  "name": "Monte Carlo Dice",
  "categories": ["math"],
  "implementations": {
    "python": ""
  },
  "contributors": [
    {
      "name": "Dhruv Manilawala",
      "email": "dhruvmanila@gmail.com",
      "commits": 1
    },
    {
      "name": "Naveen M V",
      "email": "30305957+naviji@users.noreply.github.com",
      "commits": 1
    },
    {
      "name": "Christian Clauss",
      "email": "cclauss@me.com",
      "commits": 2
    }
  ],
  "explanationUrl": {}
}
